jwt/__init__.py
jwt/__main__.py
jwt/algorithms.py
jwt/api_jwk.py
jwt/api_jws.py
jwt/api_jwt.py
jwt/compat.py
jwt/exceptions.py
jwt/help.py
jwt/jwks_client.py
jwt/utils.py
jwt/contrib/__init__.py
jwt/contrib/algorithms/__init__.py
jwt/contrib/algorithms/py_ecdsa.py
jwt/contrib/algorithms/py_ed25519.py
jwt/contrib/algorithms/pycrypto.py
privex_pyjwt-2.0.0.dist-info/AUTHORS.rst
privex_pyjwt-2.0.0.dist-info/LICENSE
privex_pyjwt-2.0.0.dist-info/METADATA
privex_pyjwt-2.0.0.dist-info/WHEEL
privex_pyjwt-2.0.0.dist-info/entry_points.txt
privex_pyjwt-2.0.0.dist-info/top_level.txt
privex_pyjwt-2.0.0.dist-info/RECORD
