Metadata-Version: 2.1
Name: privex-pyjwt
Version: 2.0.0
Summary: JSON Web Token implementation in Python (fork of PyJWT)
Home-page: https://github.com/Privex/pyjwt
Author: Chris (Someguy123) @ Privex
Author-email: chris@privex.io
License: MIT
Keywords: jwt json web token security signing
Platform: UNKNOWN
Classifier: Development Status :: 5 - Production/Stable
Classifier: Intended Audience :: Developers
Classifier: Natural Language :: English
Classifier: License :: OSI Approved :: MIT License
Classifier: Programming Language :: Python
Classifier: Programming Language :: Python :: 2.7
Classifier: Programming Language :: Python :: 3.4
Classifier: Programming Language :: Python :: 3.5
Classifier: Programming Language :: Python :: 3.6
Classifier: Programming Language :: Python :: 3.7
Classifier: Topic :: Utilities
Requires-Python: >=2.7, !=3.0.*, !=3.1.*, !=3.2.*, !=3.3.*
Provides-Extra: crypto
Requires-Dist: cryptography (>=1.4) ; extra == 'crypto'
Provides-Extra: dev
Requires-Dist: pytest (<5.0.0,>=4.0.1) ; extra == 'dev'
Requires-Dist: pytest-cov (<3.0.0,>=2.6.0) ; extra == 'dev'
Requires-Dist: requests-mock ; extra == 'dev'
Requires-Dist: cryptography (>=1.4) ; extra == 'dev'
Requires-Dist: mypy ; extra == 'dev'
Requires-Dist: pre-commit ; extra == 'dev'
Provides-Extra: tests
Requires-Dist: pytest (<5.0.0,>=4.0.1) ; extra == 'tests'
Requires-Dist: pytest-cov (<3.0.0,>=2.6.0) ; extra == 'tests'
Requires-Dist: requests-mock ; extra == 'tests'
